envoy/dependency/cve_scan/__init__.py
envoy/dependency/cve_scan/exceptions.py
envoy/dependency/cve_scan/py.typed
envoy/dependency/cve_scan/abstract/__init__.py
envoy/dependency/cve_scan/abstract/checker.py
envoy/dependency/cve_scan/abstract/cpe.py
envoy/dependency/cve_scan/abstract/cve.py
envoy/dependency/cve_scan/abstract/dependency.py
envoy/dependency/cve_scan/abstract/typing.py
envoy/dependency/cve_scan/abstract/version_matcher.py
envoy.dependency.cve_scan-0.0.4.dist-info/METADATA
envoy.dependency.cve_scan-0.0.4.dist-info/WHEEL
envoy.dependency.cve_scan-0.0.4.dist-info/namespace_packages.txt
envoy.dependency.cve_scan-0.0.4.dist-info/top_level.txt
envoy.dependency.cve_scan-0.0.4.dist-info/RECORD
