Metadata-Version: 2.1
Name: envoy.dependency.cve-scan
Version: 0.0.4
Summary: "CVE scanner used in Envoy proxy's CI"
Home-page: https://github.com/envoyproxy/pytooling/tree/main/envoy.dependency.cve_scan
Author: Ryan Northey
Author-email: ryan@synca.io
Maintainer: Ryan Northey
Maintainer-email: ryan@synca.io
License: Apache Software License 2.0
Platform: UNKNOWN
Requires-Dist: abstracts (>=0.0.12)
Requires-Dist: aio.core (>=0.2.0)
Requires-Dist: aio.run.checker (>=0.2.1)
Requires-Dist: aiohttp
Requires-Dist: envoy.base.utils (>=0.0.13)
Requires-Dist: jinja2
Requires-Dist: packaging
